<?xml version="1.0" encoding="utf-8" ?>
<dwsync>
<file name="config_functions.lib.php" server="www.dmedia.zju.edu.cn" local="130456524810854789" remote="130420399200000000" Dst="0" />
<file name="ConfigFile.class.php" server="www.dmedia.zju.edu.cn" local="130420399200000000" remote="130420399200000000" Dst="0" />
<file name="FormDisplay.class.php" server="www.dmedia.zju.edu.cn" local="130420399200000000" remote="130420399200000000" Dst="0" />
<file name="FormDisplay.tpl.php" server="www.dmedia.zju.edu.cn" local="130420399800000000" remote="130420399800000000" Dst="0" />
<file name="messages.inc.php" server="www.dmedia.zju.edu.cn" local="130420399800000000" remote="130420399800000000" Dst="0" />
<file name="setup.forms.php" server="www.dmedia.zju.edu.cn" local="130420399800000000" remote="130420399800000000" Dst="0" />
<file name="user_preferences.forms.php" server="www.dmedia.zju.edu.cn" local="130420399800000000" remote="130420399800000000" Dst="0" />
<file name="Validator.class.php" server="www.dmedia.zju.edu.cn" local="130420400400000000" remote="130420400400000000" Dst="0" />
</dwsync>